{
  "content": [
    {
      "source": "AnalyticsRules",
      "contentType": "AnalyticRules"
    },
    {
      "source": "Parsers",
      "contentType": "Parsers"
    },
    {
      "source": "Workbooks",
      "contentType": "Workbooks"
    },
    {
      "source": "Playbooks",
      "contentType": "Playbooks"
    },
    {
      "source": "Watchlists",
      "contentType": "Watchlists"
    },
    {
      "source": "HuntingQueries",
      "contentType": "HuntingQueries"
    },
    {
      "source": "DataConnectors",
      "contentType": "DataConnectors"
    },
    {
      "source": "AutomationRules",
      "contentType": "AutomationRules"
    }
  ]
}
